LICENSE
MANIFEST.in
README.md
setup.cfg
setup.py
podiant_workflows_client.egg-info/PKG-INFO
podiant_workflows_client.egg-info/SOURCES.txt
podiant_workflows_client.egg-info/dependency_links.txt
podiant_workflows_client.egg-info/not-zip-safe
podiant_workflows_client.egg-info/requires.txt
podiant_workflows_client.egg-info/top_level.txt
workflows/__init__.py
workflows/decorators.py
workflows/entities.py
workflows/exceptions.py
workflows/files.py
workflows/flask.py
workflows/logging.py
workflows/operations.py
workflows/queues.py
workflows/settings.py
workflows/transport.py
workflows/utils.py
workflows/views.py
workflows/workers.py
workflows/workflows.py