Metadata-Version: 2.1
Name: podiant-workflows-client
Version: 3.6.0
Summary: A set of tools for creating a Flask app compatible with the Podiant workflows API
Home-page: https://git.steadman.io/podiant/podiant-workflows-client
Author: Mark Steadman
Author-email: mark@podiant.co
License: MIT
Keywords: podiant-workflows
Platform: UNKNOWN
Classifier: Development Status :: 3 - Alpha
Classifier: Framework :: Flask
Classifier: Intended Audience :: Developers
Classifier: License :: OSI Approved :: BSD License
Classifier: Natural Language :: English
Classifier: Programming Language :: Python :: 3
Classifier: Programming Language :: Python :: 3.4
Classifier: Programming Language :: Python :: 3.5
Classifier: Programming Language :: Python :: 3.6
